{
  "permalink": "/blog/禁止折腾！",
  "editUrl": "https://github.com/frankelinli/frankelinli.github.io/edit/main/blog/2024/04-12-禁止折腾！.md",
  "source": "@site/blog/2024/04-12-禁止折腾！.md",
  "title": "禁止折腾！",
  "description": "不要再折腾插件、主题了！！费力不讨好！投入时间和金钱，没产出！",
  "date": "2024-04-12T22:19:00.000Z",
  "tags": [],
  "readingTime": 0.28,
  "hasTruncateMarker": true,
  "authors": [],
  "frontMatter": {
    "date": "2024-04-12 22:19",
    "slug": "禁止折腾！"
  },
  "unlisted": false,
  "lastUpdatedAt": 1539502055000,
  "prevItem": {
    "title": "第一次做头等舱",
    "permalink": "/blog/第一次做头等舱"
  },
  "nextItem": {
    "title": "python猜数字游戏源码",
    "permalink": "/blog/python猜数字游戏源码"
  }
}